{
  "project_info": {
    "project_number": "1095322656158",
    "project_id": "localmarkettracker",
    "storage_bucket": "localmarkettracker.firebasestorage.app"
  },
  "client": [
    {
      "client_info": {
        "mobilesdk_app_id": "1:1095322656158:android:02522dbc741b5598124a8f",
        "android_client_info": {
          "package_name": "com.example.localmarkettracker"
        }
      },
      "oauth_client": [],
      "api_key": [
        {
          "current_key": "AIzaSyAo5AlKXPpDwz7PXw62bKfK335-5ZeMDqo"
        }
      ],
      "services": {
        "appinvite_service": {
          "other_platform_oauth_client": []
        }
      }
    }
  ],
  "configuration_version": "1"
}